treemaker/__init__.py
treemaker/test_treemaker.py
treemaker/treemaker.py
treemaker-1.4.dist-info/LICENSE
treemaker-1.4.dist-info/METADATA
treemaker-1.4.dist-info/WHEEL
treemaker-1.4.dist-info/entry_points.txt
treemaker-1.4.dist-info/top_level.txt
treemaker-1.4.dist-info/zip-safe
treemaker-1.4.dist-info/RECORD
