Metadata-Version: 2.1
Name: treemaker
Version: 1.4
Summary: A python tool for generating a Newick formatted tree from alist of classifications
Home-page: https://github.com/SimonGreenhill/treemaker
Author: Simon J. Greenhill
Author-email: simon@simon.net.nz
License: BSD
Keywords: phylogenetics newick taxonomy
Platform: UNKNOWN
Classifier: Intended Audience :: Science/Research
Classifier: License :: OSI Approved :: BSD License
Classifier: Topic :: Scientific/Engineering
Classifier: Topic :: Scientific/Engineering :: Bio-Informatics
Classifier: Topic :: Software Development :: Libraries :: Python Modules
Classifier: Programming Language :: Python :: 2
Classifier: Programming Language :: Python :: 2.7
Classifier: Programming Language :: Python :: 3
Classifier: Programming Language :: Python :: 3.4
Classifier: Programming Language :: Python :: 3.5
Classifier: Programming Language :: Python :: 3.6
Classifier: Programming Language :: Python :: 3.7
